doc_json_sdk/__init__.py
doc_json_sdk/encoder/DocumentEncoder.py
doc_json_sdk/encoder/__init__.py
doc_json_sdk/fonts/__init__.py
doc_json_sdk/handler/__init__.py
doc_json_sdk/handler/document_handler.py
doc_json_sdk/handler/document_handler_interface.py
doc_json_sdk/handler/document_private_handler.py
doc_json_sdk/loader/__init__.py
doc_json_sdk/loader/document_model_loader.py
doc_json_sdk/loader/multi_document_loader.py
doc_json_sdk/model/__init__.py
doc_json_sdk/model/document_model.py
doc_json_sdk/model/base/__init__.py
doc_json_sdk/model/base/normal_page.py
doc_json_sdk/model/base/pos_model.py
doc_json_sdk/model/doc/__init__.py
doc_json_sdk/model/doc/doc_info_model.py
doc_json_sdk/model/doc/page_model.py
doc_json_sdk/model/enums/__init__.py
doc_json_sdk/model/enums/alignment_enum.py
doc_json_sdk/model/enums/data_source_enum.py
doc_json_sdk/model/enums/document_type_enum.py
doc_json_sdk/model/enums/font_name_enum.py
doc_json_sdk/model/enums/layout_relation_enum.py
doc_json_sdk/model/enums/layout_sub_type_enum.py
doc_json_sdk/model/enums/layout_type_enum.py
doc_json_sdk/model/enums/normal_page_enum.py
doc_json_sdk/model/layout/layout_model.py
doc_json_sdk/model/layout/image/image_layout_model.py
doc_json_sdk/model/layout/paragraph/block.py
doc_json_sdk/model/layout/paragraph/paragraph_layout_model.py
doc_json_sdk/model/layout/paragraph/word_info.py
doc_json_sdk/model/layout/table/cell.py
doc_json_sdk/model/layout/table/table_layout_model.py
doc_json_sdk/model/logic/kv_ext_info.py
doc_json_sdk/model/logic/kv_model.py
doc_json_sdk/model/logic/logic_info.py
doc_json_sdk/model/logic/logic_model.py
doc_json_sdk/model/logic/table_kv_model.py
doc_json_sdk/model/style/style_model.py
doc_json_sdk/render/__init__.py
doc_json_sdk/render/document_model_render.py
doc_json_sdk/utils/__init__.py
doc_json_sdk/utils/hash.py
doc_json_sdk/utils/log_util.py
docmind_doc_json_sdk-1.1.2.dist-info/METADATA
docmind_doc_json_sdk-1.1.2.dist-info/WHEEL
docmind_doc_json_sdk-1.1.2.dist-info/licenses/LICENSE
docmind_doc_json_sdk-1.1.2.dist-info/RECORD
