Metadata-Version: 2.3
Name: docmind-doc-json-sdk
Version: 1.1.2
Summary: doc-json-sdk 调用云上docmind解析能力
Author-email: 足溪 <sanchuan.ssc@alibaba-inc.com>
Classifier: License :: OSI Approved :: Apache Software License
Classifier: Operating System :: OS Independent
Classifier: Programming Language :: Python :: 3
Requires-Python: <4.0,>=3.9
Requires-Dist: alibabacloud-credentials==1.0.2
Requires-Dist: alibabacloud-docmind-api20220711==1.4.11
Requires-Dist: alibabacloud-tea-openapi==0.4.1
Requires-Dist: dacite>=1.8.1
Requires-Dist: deepdiff>=7.0.1
Requires-Dist: numpy>=2.0
Requires-Dist: pillow>=9.0.0
Requires-Dist: pydantic>=2.11.5
Requires-Dist: tqdm>=4.66.5
Provides-Extra: dev
Requires-Dist: pytest>=7.4.0; extra == 'dev'
